main.py
terminal_based_gmail-0.1.0.dist-info/METADATA
terminal_based_gmail-0.1.0.dist-info/WHEEL
terminal_based_gmail-0.1.0.dist-info/top_level.txt
terminal_based_gmail-0.1.0.dist-info/RECORD
