Metadata-Version: 2.4
Name: terminal-based-gmail
Version: 0.1.0
Summary: Add your description here
Requires-Python: >=3.13
Requires-Dist: google-api-python-client>=2.186.0
Requires-Dist: google-auth-httplib2>=0.2.1
Requires-Dist: google-auth-oauthlib>=1.2.3
